do/API.py
do/__init__.py
do/core/API.py
do/core/ConditionalProbabilityTable.py
do/core/Exceptions.py
do/core/Expression.py
do/core/Graph.py
do/core/Inference.py
do/core/Model.py
do/core/Types.py
do/core/Variables.py
do/core/__init__.py
do/core/helpers.py
do/deconfounding/API.py
do/deconfounding/Backdoor.py
do/deconfounding/Do.py
do/deconfounding/Exceptions.py
do/deconfounding/__init__.py
do/identification/API.py
do/identification/Exceptions.py
do/identification/Identification.py
do/identification/LatentGraph.py
do/identification/PExpression.py
do/identification/__init__.py
do_calculus-2.0.0.dist-info/METADATA
do_calculus-2.0.0.dist-info/WHEEL
do_calculus-2.0.0.dist-info/entry_points.txt
do_calculus-2.0.0.dist-info/top_level.txt
do_calculus-2.0.0.dist-info/RECORD
