Metadata-Version: 2.1
Name: do-calculus
Version: 2.0.0
Summary: A Python implementation of the do-calculus of Judea Pearl et. al.
Home-page: https://github.com/bradendubois/do-calculus
Author: Braden Dubois
Author-email: braden.dubois@usask.ca
License: UNKNOWN
Keywords: do-calculus causation statistics pearl python
Platform: UNKNOWN
Requires-Dist: PyYAML (>=5.4.0)
Requires-Dist: loguru (>=0.5.3)
Requires-Dist: numpy (>=1.19.4)
